{
  "legoCreation": [
    {
      "creation": "T-rex",
      "color": "1",
      "shape": "Dino",
      "creator": "Me",
      "id": 1
    },
    {
      "creation": "T-rex",
      "color": "4",
      "shape": "Dino",
      "creator": "Mike",
      "id": 2
    },
    {
      "creation": "T-rex",
      "color": "4",
      "shape": "Dino",
      "creator": "Mike",
      "id": 3
    },
    {
      "creation": "House",
      "color": "2",
      "shape": "Building",
      "creator": "Joni",
      "id": 4
    }
  ]
}